{
  "game": "wend",
  "number": 45,
  "date": "2026-07-23",
  "grid_size": [
    6,
    6
  ],
  "grid": [
    [
      ".",
      ".",
      "R",
      "D",
      "V",
      "K"
    ],
    [
      ".",
      "A",
      "A",
      ".",
      "A",
      "R"
    ],
    [
      "T",
      "A",
      ".",
      "A",
      "P",
      "P"
    ],
    [
      "H",
      "T",
      "E",
      ".",
      "E",
      "L"
    ],
    [
      "L",
      "E",
      ".",
      "E",
      "E",
      "."
    ],
    [
      "D",
      "E",
      "C",
      "R",
      ".",
      "."
    ]
  ],
  "words": [
    "APPLE",
    "DECREE",
    "ATHLETE",
    "AARDVARK"
  ]
}